class_factory/__init__.py
class_factory/base_class_factory.py
class_factory/class_factory_user.py
class_factory-1.0.dist-info/METADATA
class_factory-1.0.dist-info/WHEEL
class_factory-1.0.dist-info/top_level.txt
class_factory-1.0.dist-info/RECORD
