Metadata-Version: 2.1
Name: class-factory
Version: 1.0
Summary: package for factory mechanism for sub classes and auto import mechanism
Author: Marc MALBERT
Author-email: eldrad-59@hotmail.fr
Classifier: Programming Language :: Python :: 3
Classifier: Development Status :: 5 - Production/Stable
Classifier: Natural Language :: English
Classifier: Operating System :: OS Independent
